flurs/__init__.py
flurs/base.py
flurs/evaluator.py
flurs/baseline/__init__.py
flurs/baseline/popular.py
flurs/baseline/random.py
flurs/data/__init__.py
flurs/data/entity.py
flurs/datasets/__init__.py
flurs/datasets/movielens.py
flurs/model/__init__.py
flurs/model/bprmf.py
flurs/model/factorization_machine.py
flurs/model/matrix_factorization.py
flurs/model/online_sketch.py
flurs/model/user_knn.py
flurs/recommender/__init__.py
flurs/recommender/bprmf.py
flurs/recommender/factorization_machine.py
flurs/recommender/matrix_factorization.py
flurs/recommender/online_sketch.py
flurs/recommender/user_knn.py
flurs/utils/__init__.py
flurs/utils/feature_hash.py
flurs/utils/metric.py
flurs/utils/projection.py
flurs-0.0.5.dist-info/LICENSE
flurs-0.0.5.dist-info/METADATA
flurs-0.0.5.dist-info/WHEEL
flurs-0.0.5.dist-info/top_level.txt
flurs-0.0.5.dist-info/RECORD
