Metadata-Version: 2.1
Name: flurs
Version: 0.0.5
Summary: A library for streaming recommendation algorithms
Home-page: https://github.com/takuti/flurs
Author: Takuya Kitazawa
Author-email: k.takuti@gmail.com
Maintainer: Takuya Kitazawa
Maintainer-email: k.takuti@gmail.com
License: MIT
Download-URL: https://pypi.org/project/flurs/#files
Platform: UNKNOWN
Classifier: Intended Audience :: Science/Research
Classifier: Intended Audience :: Developers
Classifier: License :: OSI Approved
Classifier: Programming Language :: Python
Classifier: Topic :: Scientific/Engineering
Classifier: Development Status :: 4 - Beta
Classifier: Operating System :: Microsoft :: Windows
Classifier: Operating System :: POSIX
Classifier: Operating System :: Unix
Classifier: Operating System :: MacOS
Classifier: Programming Language :: Python :: 3
Classifier: Programming Language :: Python :: 3.7
Classifier: Programming Language :: Python :: 3.8
Classifier: Programming Language :: Python :: 3.9
License-File: LICENSE
Requires-Dist: numpy (>=1.14.6)
Requires-Dist: scipy (>=1.6.3)
Requires-Dist: scikit-learn (>=1.0)
Requires-Dist: mmh3 (>=3.0.0)
Provides-Extra: docs
Requires-Dist: sphinx-rtd-theme ; extra == 'docs'
Requires-Dist: sphinx-gallery ; extra == 'docs'
Provides-Extra: tests
Requires-Dist: black (>=21.6b0) ; extra == 'tests'
Requires-Dist: pre-commit ; extra == 'tests'
Requires-Dist: pytest-remotedata (==0.3.2) ; extra == 'tests'
Requires-Dist: mypy (>=0.770) ; extra == 'tests'
Requires-Dist: flake8 (>=3.8.2) ; extra == 'tests'
Requires-Dist: pytest (>=5.0.1) ; extra == 'tests'
